sops_wrapper.py
sops_wrapper-0.1.1.dist-info/LICENSE
sops_wrapper-0.1.1.dist-info/METADATA
sops_wrapper-0.1.1.dist-info/WHEEL
sops_wrapper-0.1.1.dist-info/entry_points.txt
sops_wrapper-0.1.1.dist-info/top_level.txt
sops_wrapper-0.1.1.dist-info/zip-safe
sops_wrapper-0.1.1.dist-info/RECORD
