Metadata-Version: 2.1
Name: sops-wrapper
Version: 0.1.1
Summary: A small wrapper around sops
Home-page: https://github.com/mortbauer/sops-wrapper
Author: Martin Ortbauer
Author-email: martin@villagefarmer.net
License: MIT
Classifier: Intended Audience :: Developers
Classifier: License :: OSI Approved :: MIT License
Classifier: Operating System :: OS Independent
Classifier: Programming Language :: Python :: 3
Classifier: Programming Language :: Python :: 3.7
Classifier: Programming Language :: Python :: 3.8
Requires-Python: >=3.6
License-File: LICENSE
Requires-Dist: ruamel.yaml
Provides-Extra: dev
Requires-Dist: black ; extra == 'dev'
Requires-Dist: check-manifest ; extra == 'dev'
Requires-Dist: flake8 ; extra == 'dev'
Requires-Dist: flake8-bugbear ; extra == 'dev'
Requires-Dist: flake8-import-order ; extra == 'dev'
Requires-Dist: isort[pyproject] ; extra == 'dev'
Requires-Dist: twine ; extra == 'dev'
Requires-Dist: wheel ; extra == 'dev'
Requires-Dist: pytest ; extra == 'dev'
Requires-Dist: pytest-cov ; extra == 'dev'
Provides-Extra: lint
Requires-Dist: black ; extra == 'lint'
Requires-Dist: check-manifest ; extra == 'lint'
Requires-Dist: flake8 ; extra == 'lint'
Requires-Dist: flake8-bugbear ; extra == 'lint'
Requires-Dist: flake8-import-order ; extra == 'lint'
Requires-Dist: isort[pyproject] ; extra == 'lint'
Provides-Extra: release
Requires-Dist: twine ; extra == 'release'
Requires-Dist: wheel ; extra == 'release'
Provides-Extra: test
Requires-Dist: pytest ; extra == 'test'
Requires-Dist: pytest-cov ; extra == 'test'
